{
  "imports": "import Heading from \"@kiwicom/orbit-components/lib/Heading\";\nimport RatingStars from \"@kiwicom/orbit-components/lib/RatingStars\";\nimport Stack from \"@kiwicom/orbit-components/lib/Stack\";",
  "example": "(): React.Node => (\n  <Stack direction=\"column\">\n    <Stack direction=\"column\">\n      <Heading type=\"title3\" as=\"h3\">\n        Small\n      </Heading>\n      <RatingStars rating={3} showEmpty />\n    </Stack>\n    <Stack direction=\"column\">\n      <Heading type=\"title3\" as=\"h3\">\n        Medium\n      </Heading>\n      <RatingStars size=\"medium\" rating={3} showEmpty />\n    </Stack>\n    <Stack direction=\"column\">\n      <Heading type=\"title3\" as=\"h3\">\n        Large\n      </Heading>\n      <RatingStars size=\"large\" rating={3} showEmpty />\n    </Stack>\n  </Stack>\n)\n",
  "info": {
    "title": "Sizes",
    "description": "The stars can be small (the default), medium, or large."
  }
}
