{
  "imports": "import CountryFlag from \"@kiwicom/orbit-components/lib/CountryFlag\";\nimport InputField from \"@kiwicom/orbit-components/lib/InputField\";\nimport InputGroup from \"@kiwicom/orbit-components/lib/InputGroup\";\nimport Select from \"@kiwicom/orbit-components/lib/Select\";\nimport Stack from \"@kiwicom/orbit-components/lib/Stack\";",
  "example": "(): React.Node => {\n  const [country, setCountry] = React.useState(\"\")\n  const [country2, setCountry2] = React.useState(\"\")\n\n  const setPrefix = (countryCode) => {\n    let calculatedPrefix\n\n    switch (countryCode) {\n      case \"dz\":\n        calculatedPrefix = \"+213\"\n        break\n\n      case \"bo\":\n        calculatedPrefix = \"+591\"\n        break\n\n      case \"hr\":\n        calculatedPrefix = \"+385\"\n        break\n\n      case \"id\":\n        calculatedPrefix = \"+62\"\n        break\n\n      case \"mx\":\n        calculatedPrefix = \"+52\"\n        break\n\n      default:\n        calculatedPrefix = \"\"\n    }\n\n    return calculatedPrefix\n  }\n\n  const countryPrefix = setPrefix(country)\n  const countryPrefix2 = setPrefix(country2)\n  return (\n    <Stack>\n      <InputGroup label=\"Phone number\">\n        <Select\n          value={country}\n          customValueText={countryPrefix}\n          placeholder=\"Country prefix\"\n          options={[\n            {\n              label: \"Algeria +213\",\n              value: \"dz\",\n            },\n            {\n              label: \"Bolivia +591\",\n              value: \"bo\",\n            },\n            {\n              label: \"Croatia +385\",\n              value: \"hr\",\n            },\n            {\n              label: \"Indonesia +62\",\n              value: \"id\",\n            },\n            {\n              label: \"Mexico +52\",\n              value: \"mx\",\n            },\n          ]}\n          onChange={(event) => setCountry(event.target.value)}\n          prefix={<CountryFlag code={country || \"anywhere\"} />}\n        />\n        <InputField placeholder=\"123456789\" type=\"number\" inputMode=\"tel\" />\n      </InputGroup>\n      <InputGroup size=\"small\" label=\"Phone number\">\n        <Select\n          value={country2}\n          customValueText={countryPrefix2}\n          placeholder=\"Country prefix\"\n          options={[\n            {\n              label: \"Algeria +213\",\n              value: \"dz\",\n            },\n            {\n              label: \"Bolivia +591\",\n              value: \"bo\",\n            },\n            {\n              label: \"Croatia +385\",\n              value: \"hr\",\n            },\n            {\n              label: \"Indonesia +62\",\n              value: \"id\",\n            },\n            {\n              label: \"Mexico +52\",\n              value: \"mx\",\n            },\n          ]}\n          onChange={(event) => setCountry2(event.target.value)}\n          prefix={<CountryFlag code={country2 || \"anywhere\"} />}\n        />\n        <InputField placeholder=\"123456789\" type=\"number\" inputMode=\"tel\" />\n      </InputGroup>\n    </Stack>\n  )\n}\n",
  "info": {
    "title": "Sizes",
    "description": "Input groups can be either normal sized or small. Set the size for the group and not for its children."
  }
}
